clerk_backend_api_client/__init__.py
clerk_backend_api_client/api/__init__.py
clerk_backend_api_client/api/actor_tokens/__init__.py
clerk_backend_api_client/api/actor_tokens/create_actor_token.py
clerk_backend_api_client/api/actor_tokens/revoke_actor_token.py
clerk_backend_api_client/api/allow_list_block_list/__init__.py
clerk_backend_api_client/api/allow_list_block_list/create_allowlist_identifier.py
clerk_backend_api_client/api/allow_list_block_list/create_blocklist_identifier.py
clerk_backend_api_client/api/allow_list_block_list/delete_allowlist_identifier.py
clerk_backend_api_client/api/allow_list_block_list/delete_blocklist_identifier.py
clerk_backend_api_client/api/allow_list_block_list/list_allowlist_identifiers.py
clerk_backend_api_client/api/allow_list_block_list/list_blocklist_identifiers.py
clerk_backend_api_client/api/beta_features/__init__.py
clerk_backend_api_client/api/beta_features/change_production_instance_domain.py
clerk_backend_api_client/api/beta_features/update_instance_auth_config.py
clerk_backend_api_client/api/beta_features/update_production_instance_domain.py
clerk_backend_api_client/api/clients/__init__.py
clerk_backend_api_client/api/clients/get_client.py
clerk_backend_api_client/api/clients/get_client_list.py
clerk_backend_api_client/api/clients/verify_client.py
clerk_backend_api_client/api/domains/__init__.py
clerk_backend_api_client/api/domains/add_domain.py
clerk_backend_api_client/api/domains/delete_domain.py
clerk_backend_api_client/api/domains/list_domains.py
clerk_backend_api_client/api/domains/update_domain.py
clerk_backend_api_client/api/email_addresses/__init__.py
clerk_backend_api_client/api/email_addresses/create_email_address.py
clerk_backend_api_client/api/email_addresses/delete_email_address.py
clerk_backend_api_client/api/email_addresses/get_email_address.py
clerk_backend_api_client/api/email_addresses/update_email_address.py
clerk_backend_api_client/api/email_sms_templates/__init__.py
weebuild_clerk_backend_api_client-1.0.0.dist-info/METADATA
weebuild_clerk_backend_api_client-1.0.0.dist-info/WHEEL
weebuild_clerk_backend_api_client-1.0.0.dist-info/RECORD
